django_octicons-1.0.2.dist-info/METADATA
django_octicons-1.0.2.dist-info/RECORD
django_octicons-1.0.2.dist-info/WHEEL
django_octicons-1.0.2.dist-info/top_level.txt
octicons/__init__.py
octicons/__version__.py
octicons/apps.py
octicons/data.json
octicons/templatetags/__init__.py
octicons/templatetags/octicons.py
