Metadata-Version: 2.1
Name: django-octicons
Version: 1.0.2
Summary: Django templatetags for GitHub's Octicons.
Home-page: https://github.com/sanketsaurav/django-octicons
Author: Sanket Saurav
Author-email: sanketsaurav@gmail.com
License: MIT
Keywords: django icons github octicons templatetags
Platform: UNKNOWN
Classifier: Development Status :: 4 - Beta
Classifier: Intended Audience :: Developers
Classifier: Topic :: Software Development :: Libraries :: Python Modules
Classifier: Environment :: Web Environment
Classifier: Topic :: Internet
Classifier: License :: OSI Approved :: MIT License
Classifier: Operating System :: OS Independent
Classifier: Programming Language :: Python
Classifier: Programming Language :: Python :: 2.7
Classifier: Programming Language :: Python :: 3.4
Classifier: Programming Language :: Python :: 3.5
Classifier: Programming Language :: Python :: 3.6
Classifier: Framework :: Django
Classifier: Framework :: Django :: 1.11
Classifier: Framework :: Django :: 2.0
Classifier: Framework :: Django :: 2.1
Requires-Python: >=2.7.0
